submariner/__about__.py
submariner/__init__.py
submariner/env.py
submariner/main.py
submariner/test.py
submariner/customtypes/__init__.py
submariner/customtypes/codeblock.py
submariner/customtypes/command.py
submariner/customtypes/crashcourse.py
submariner/customtypes/keypoint.py
submariner/customtypes/response.py
submariner/interfaces/__init__.py
submariner/interfaces/commands.py
submariner/interfaces/module.py
submariner/interfaces/pypi.py
submariner/interfaces/virtualenv.py
submariner-0.1.1.dist-info/METADATA
submariner-0.1.1.dist-info/WHEEL
submariner-0.1.1.dist-info/entry_points.txt
submariner-0.1.1.dist-info/licenses/LICENSE.txt
submariner-0.1.1.dist-info/RECORD
