Metadata-Version: 2.4
Name: submariner
Version: 0.1.1
Summary: A tool to explore python modules
Project-URL: Documentation, https://github.com/Buchimi/submariner#readme
Project-URL: Issues, https://github.com/Buchimi/submariner/issues
Project-URL: Source, https://github.com/Buchimi/submariner
Author-email: Buchimi <stormzzy900@gmail.com>
License-Expression: MIT
License-File: LICENSE.txt
Classifier: Development Status :: 4 - Beta
Classifier: Programming Language :: Python
Classifier: Programming Language :: Python :: 3.9
Classifier: Programming Language :: Python :: 3.10
Classifier: Programming Language :: Python :: 3.11
Classifier: Programming Language :: Python :: 3.12
Requires-Python: >=3.8
Requires-Dist: dotenv
Requires-Dist: langchain[google-genai]
Requires-Dist: rich
Requires-Dist: typer
